morsels/__init__.py
morsels/apps.py
morsels/blocks.py
morsels/model_porter.py
morsels/models.py
morsels/migrations/0001_initial.py
morsels/migrations/__init__.py
morsels/templates/morsels/base.html
morsels/templates/morsels/blocks/morsel_block.html
morsels/templates/morsels/blocks/morsel_content_stream.html
morsels/templatetags/__init__.py
morsels/templatetags/morsel_tags.py
morsels-4.1.0.dist-info/AUTHORS.txt
morsels-4.1.0.dist-info/LICENSE.txt
morsels-4.1.0.dist-info/METADATA
morsels-4.1.0.dist-info/WHEEL
morsels-4.1.0.dist-info/top_level.txt
morsels-4.1.0.dist-info/zip-safe
morsels-4.1.0.dist-info/RECORD
