Metadata-Version: 2.1
Name: morsels
Version: 4.1.0
Summary: A Wagtail app for re-usable page morsels.
Home-page: https://github.com/high-dimensional/morsels
Author: High Dimensional Neurology Group, UCL
Author-email: pypi@highdimensional.net
License: BSD-3-Clause
Platform: any
Classifier: Framework :: Django
Classifier: Framework :: Wagtail
Classifier: Programming Language :: Python :: 3
Classifier: Programming Language :: Python :: 3.8
Classifier: License :: OSI Approved :: BSD License
Classifier: Operating System :: OS Independent
Requires-Python: >=3.8
License-File: LICENSE.txt
License-File: AUTHORS.txt
Requires-Dist: Django (<4.2,>=4.1)
Requires-Dist: wagtail (<4.2,>=4.1)
Requires-Dist: wagtail-block-model-field (<4.2,>=4.1)
Requires-Dist: wagtail-dynamic-stream-block (<4.2,>=4.1)
Requires-Dist: model-porter (<4.2,>=4.1)
